{
  "scenario_id": "france_germany_runner_up_EI",
  "description": "Germany finishes 2nd in Group E (Ecuador wins) AND France finishes 2nd in Group I (Norway wins). All other groups resolve as seeded.",
  "deviating_group": "E",
  "favourite": "Germany",
  "upset_winner": "Ecuador",
  "computed_at": "2026-06-11T13:36:49+00:00",
  "standings": {
    "A": [
      "Mexico",
      "Czechia",
      "South Korea",
      "South Africa"
    ],
    "B": [
      "Switzerland",
      "Canada",
      "Bosnia and Herzegovina",
      "Qatar"
    ],
    "C": [
      "Brazil",
      "Morocco",
      "Scotland",
      "Haiti"
    ],
    "D": [
      "United States",
      "Turkey",
      "Paraguay",
      "Australia"
    ],
    "E": [
      "Ecuador",
      "Germany",
      "Ivory Coast",
      "Curacao"
    ],
    "F": [
      "Netherlands",
      "Japan",
      "Sweden",
      "Tunisia"
    ],
    "G": [
      "Belgium",
      "Egypt",
      "Iran",
      "New Zealand"
    ],
    "H": [
      "Spain",
      "Uruguay",
      "Cape Verde",
      "Saudi Arabia"
    ],
    "I": [
      "Norway",
      "France",
      "Senegal",
      "Iraq"
    ],
    "J": [
      "Argentina",
      "Austria",
      "Algeria",
      "Jordan"
    ],
    "K": [
      "Portugal",
      "Colombia",
      "DR Congo",
      "Uzbekistan"
    ],
    "L": [
      "England",
      "Croatia",
      "Ghana",
      "Panama"
    ]
  },
  "survival": {
    "Spain": {
      "R32": 1.0,
      "R16": 0.774991,
      "QF": 0.570367,
      "SF": 0.437091,
      "F": 0.310261,
      "Win": 0.180709
    },
    "England": {
      "R32": 1.0,
      "R16": 0.72022,
      "QF": 0.529122,
      "SF": 0.278092,
      "F": 0.170488,
      "Win": 0.106063
    },
    "Portugal": {
      "R32": 1.0,
      "R16": 0.770738,
      "QF": 0.563156,
      "SF": 0.34306,
      "F": 0.174084,
      "Win": 0.102623
    },
    "France": {
      "R32": 1.0,
      "R16": 0.617361,
      "QF": 0.372091,
      "SF": 0.23815,
      "F": 0.154203,
      "Win": 0.101169
    },
    "Argentina": {
      "R32": 1.0,
      "R16": 0.673073,
      "QF": 0.486818,
      "SF": 0.290711,
      "F": 0.146038,
      "Win": 0.085373
    },
    "Brazil": {
      "R32": 1.0,
      "R16": 0.651976,
      "QF": 0.322125,
      "SF": 0.190835,
      "F": 0.114459,
      "Win": 0.069705
    },
    "Netherlands": {
      "R32": 1.0,
      "R16": 0.585571,
      "QF": 0.42493,
      "SF": 0.252094,
      "F": 0.128263,
      "Win": 0.056878
    },
    "Norway": {
      "R32": 1.0,
      "R16": 0.693797,
      "QF": 0.424385,
      "SF": 0.242623,
      "F": 0.118519,
      "Win": 0.050114
    },
    "Germany": {
      "R32": 1.0,
      "R16": 0.382639,
      "QF": 0.186162,
      "SF": 0.098331,
      "F": 0.052633,
      "Win": 0.028692
    },
    "Belgium": {
      "R32": 1.0,
      "R16": 0.639894,
      "QF": 0.377718,
      "SF": 0.147883,
      "F": 0.073595,
      "Win": 0.026869
    },
    "Ecuador": {
      "R32": 1.0,
      "R16": 0.595396,
      "QF": 0.289628,
      "SF": 0.144588,
      "F": 0.060423,
      "Win": 0.021287
    },
    "Morocco": {
      "R32": 1.0,
      "R16": 0.414429,
      "QF": 0.268377,
      "SF": 0.136634,
      "F": 0.058362,
      "Win": 0.021094
    },
    "Colombia": {
      "R32": 1.0,
      "R16": 0.556096,
      "QF": 0.194417,
      "SF": 0.109489,
      "F": 0.054572,
      "Win": 0.019964
    },
    "United States": {
      "R32": 1.0,
      "R16": 0.587845,
      "QF": 0.291687,
      "SF": 0.099607,
      "F": 0.04421,
      "Win": 0.013929
    },
    "Mexico": {
      "R32": 1.0,
      "R16": 0.625239,
      "QF": 0.229617,
      "SF": 0.075838,
      "F": 0.031773,
      "Win": 0.013644
    },
    "Switzerland": {
      "R32": 1.0,
      "R16": 0.629726,
      "QF": 0.2361,
      "SF": 0.099233,
      "F": 0.031811,
      "Win": 0.012783
    },
    "Japan": {
      "R32": 1.0,
      "R16": 0.348024,
      "QF": 0.119622,
      "SF": 0.053111,
      "F": 0.023923,
      "Win": 0.011024
    },
    "Uruguay": {
      "R32": 1.0,
      "R16": 0.326927,
      "QF": 0.181969,
      "SF": 0.077861,
      "F": 0.025901,
      "Win": 0.010736
    },
    "Turkey": {
      "R32": 1.0,
      "R16": 0.57821,
      "QF": 0.20879,
      "SF": 0.084655,
      "F": 0.026355,
      "Win": 0.010334
    },
    "Croatia": {
      "R32": 1.0,
      "R16": 0.443904,
      "QF": 0.133232,
      "SF": 0.067634,
      "F": 0.029983,
      "Win": 0.009432
    },
    "Senegal": {
      "R32": 1.0,
      "R16": 0.27978,
      "QF": 0.145238,
      "SF": 0.044282,
      "F": 0.017372,
      "Win": 0.006997
    },
    "Austria": {
      "R32": 1.0,
      "R16": 0.225009,
      "QF": 0.101985,
      "SF": 0.05019,
      "F": 0.021487,
      "Win": 0.006463
    },
    "Paraguay": {
      "R32": 1.0,
      "R16": 0.404604,
      "QF": 0.15918,
      "SF": 0.064659,
      "F": 0.021371,
      "Win": 0.005721
    },
    "Canada": {
      "R32": 1.0,
      "R16": 0.516354,
      "QF": 0.162027,
      "SF": 0.060047,
      "F": 0.01796,
      "Win": 0.004276
    },
    "Algeria": {
      "R32": 1.0,
      "R16": 0.412155,
      "QF": 0.168756,
      "SF": 0.044903,
      "F": 0.016134,
      "Win": 0.003881
    },
    "South Korea": {
      "R32": 1.0,
      "R16": 0.360106,
      "QF": 0.161838,
      "SF": 0.043202,
      "F": 0.015566,
      "Win": 0.003757
    },
    "Sweden": {
      "R32": 1.0,
      "R16": 0.306203,
      "QF": 0.126808,
      "SF": 0.04796,
      "F": 0.014625,
      "Win": 0.003562
    },
    "Czechia": {
      "R32": 1.0,
      "R16": 0.483646,
      "QF": 0.144666,
      "SF": 0.051395,
      "F": 0.014669,
      "Win": 0.003305
    },
    "Egypt": {
      "R32": 1.0,
      "R16": 0.42179,
      "QF": 0.122423,
      "SF": 0.04085,
      "F": 0.010005,
      "Win": 0.003209
    },
    "Ivory Coast": {
      "R32": 1.0,
      "R16": 0.229262,
      "QF": 0.10429,
      "SF": 0.034705,
      "F": 0.008355,
      "Win": 0.002641
    },
    "Scotland": {
      "R32": 1.0,
      "R16": 0.374761,
      "QF": 0.096023,
      "SF": 0.02136,
      "F": 0.006469,
      "Win": 0.002025
    },
    "Iran": {
      "R32": 1.0,
      "R16": 0.370274,
      "QF": 0.096454,
      "SF": 0.028925,
      "F": 0.006131,
      "Win": 0.001742
    }
  },
  "delta_from_baseline": {
    "France": {
      "R32": 0.0,
      "R16": -0.213926,
      "QF": -0.186913,
      "SF": -0.168735,
      "F": -0.109821,
      "Win": -0.060725
    },
    "Norway": {
      "R32": 0.0,
      "R16": 0.119486,
      "QF": 0.174834,
      "SF": 0.123527,
      "F": 0.060881,
      "Win": 0.02506
    },
    "Germany": {
      "R32": 0.0,
      "R16": -0.331932,
      "QF": -0.130357,
      "SF": -0.098558,
      "F": -0.053465,
      "Win": -0.024178
    },
    "Spain": {
      "R32": 0.0,
      "R16": 0.0,
      "QF": 0.0,
      "SF": 0.0,
      "F": 0.046469,
      "Win": 0.020889
    },
    "Netherlands": {
      "R32": 0.0,
      "R16": 0.0,
      "QF": 0.0,
      "SF": 0.068476,
      "F": 0.03484,
      "Win": 0.013212
    },
    "Brazil": {
      "R32": 0.0,
      "R16": 0.0,
      "QF": -0.100828,
      "SF": -0.059732,
      "F": -0.035826,
      "Win": -0.013002
    },
    "Ecuador": {
      "R32": 0.0,
      "R16": 0.169707,
      "QF": 0.135132,
      "SF": 0.081847,
      "F": 0.034562,
      "Win": 0.011853
    },
    "Morocco": {
      "R32": 0.0,
      "R16": 0.0,
      "QF": 0.0,
      "SF": 0.042268,
      "F": 0.018054,
      "Win": 0.005594
    },
    "Belgium": {
      "R32": 0.0,
      "R16": 0.0,
      "QF": 0.0,
      "SF": 0.0,
      "F": 0.01605,
      "Win": 0.004527
    },
    "England": {
      "R32": 0.0,
      "R16": 0.0,
      "QF": 0.0,
      "SF": -0.038726,
      "F": -0.023741,
      "Win": -0.00345
    },
    "Colombia": {
      "R32": 0.0,
      "R16": 0.0,
      "QF": 0.0,
      "SF": 0.0,
      "F": 0.011888,
      "Win": 0.00336
    },
    "Paraguay": {
      "R32": 0.0,
      "R16": 0.119175,
      "QF": 0.088687,
      "SF": 0.036025,
      "F": 0.011907,
      "Win": 0.002989
    },
    "Japan": {
      "R32": 0.0,
      "R16": 0.0,
      "QF": -0.053378,
      "SF": -0.023699,
      "F": -0.010675,
      "Win": -0.00288
    },
    "Portugal": {
      "R32": 0.0,
      "R16": 0.0,
      "QF": 0.0,
      "SF": 0.0,
      "F": -0.014312,
      "Win": 0.002699
    },
    "United States": {
      "R32": 0.0,
      "R16": 0.0,
      "QF": 0.0,
      "SF": 0.0,
      "F": 0.010452,
      "Win": 0.002543
    },
    "Argentina": {
      "R32": 0.0,
      "R16": 0.0,
      "QF": 0.0,
      "SF": 0.0,
      "F": -0.01214,
      "Win": 0.002268
    },
    "Sweden": {
      "R32": 0.0,
      "R16": 0.13749,
      "QF": 0.072824,
      "SF": 0.027543,
      "F": 0.008399,
      "Win": 0.00192
    },
    "Croatia": {
      "R32": 0.0,
      "R16": 0.0,
      "QF": 0.0,
      "SF": 0.0,
      "F": 0.007094,
      "Win": 0.001723
    },
    "Canada": {
      "R32": 0.0,
      "R16": 0.0,
      "QF": 0.0,
      "SF": 0.02255,
      "F": 0.006744,
      "Win": 0.001382
    },
    "Austria": {
      "R32": 0.0,
      "R16": 0.0,
      "QF": 0.0,
      "SF": 0.0,
      "F": 0.005198,
      "Win": 0.001207
    },
    "Czechia": {
      "R32": 0.0,
      "R16": 0.0,
      "QF": 0.0,
      "SF": 0.019702,
      "F": 0.005623,
      "Win": 0.001091
    },
    "Algeria": {
      "R32": 0.0,
      "R16": 0.0,
      "QF": 0.0,
      "SF": 0.0,
      "F": 0.00431,
      "Win": 0.0008
    },
    "South Korea": {
      "R32": 0.0,
      "R16": 0.0,
      "QF": 0.0,
      "SF": 0.0,
      "F": 0.004152,
      "Win": 0.000773
    },
    "Mexico": {
      "R32": 0.0,
      "R16": 0.0,
      "QF": 0.0,
      "SF": -0.016344,
      "F": -0.006847,
      "Win": -0.000696
    },
    "Switzerland": {
      "R32": 0.0,
      "R16": 0.0,
      "QF": 0.0,
      "SF": 0.0,
      "F": -0.003911,
      "Win": 0.000469
    },
    "Uruguay": {
      "R32": 0.0,
      "R16": 0.0,
      "QF": 0.0,
      "SF": 0.0,
      "F": -0.003101,
      "Win": 0.000386
    },
    "Turkey": {
      "R32": 0.0,
      "R16": 0.0,
      "QF": 0.0,
      "SF": 0.0,
      "F": -0.003308,
      "Win": 0.000385
    },
    "Senegal": {
      "R32": 0.0,
      "R16": 0.0,
      "QF": 0.0,
      "SF": -0.010128,
      "F": -0.003973,
      "Win": -0.000381
    },
    "Scotland": {
      "R32": 0.0,
      "R16": 0.0,
      "QF": 0.0,
      "SF": -0.006015,
      "F": -0.001821,
      "Win": -0.000139
    },
    "Egypt": {
      "R32": 0.0,
      "R16": 0.0,
      "QF": 0.0,
      "SF": 0.0,
      "F": -0.001467,
      "Win": 0.000134
    },
    "Ivory Coast": {
      "R32": 0.0,
      "R16": 0.0,
      "QF": 0.0,
      "SF": 0.0,
      "F": -0.001237,
      "Win": 0.000111
    },
    "Iran": {
      "R32": 0.0,
      "R16": 0.0,
      "QF": 0.0,
      "SF": 0.0,
      "F": -0.000976,
      "Win": 7.7e-05
    }
  }
}